warriornetwork/__init__.py
warriornetwork/Actions/__init__.py
warriornetwork/Actions/NetworkActions/__init__.py
warriornetwork/Actions/NetworkActions/Connection/__init__.py
warriornetwork/Actions/NetworkActions/Connection/connection_actions.py
warriornetwork/Actions/NetworkActions/Diagnostics/__init__.py
warriornetwork/Actions/NetworkActions/Diagnostics/diagnostics_actions.py
warriornetwork/Actions/NetworkActions/FileOps/__init__.py
warriornetwork/Actions/NetworkActions/FileOps/file_ops_actions.py
warriornetwork/ClassUtils/__init__.py
warriornetwork/ClassUtils/ssh_utils_class.py
warriornetwork/ClassUtils/WNetwork/__init__.py
warriornetwork/ClassUtils/WNetwork/base_class.py
warriornetwork/ClassUtils/WNetwork/connection.py
warriornetwork/ClassUtils/WNetwork/diagnostics.py
warriornetwork/ClassUtils/WNetwork/file_ops.py
warriornetwork/ClassUtils/WNetwork/loging.py
warriornetwork/ClassUtils/WNetwork/network_class.py
warriornetwork/ClassUtils/WNetwork/warrior_cli_class.py
warriornetwork/ProductDrivers/__init__.py
warriornetwork/ProductDrivers/network_driver.py
warriornetwork/Utils/__init__.py
warriornetwork/Utils/cli_Utils.py
warriornetwork-1.0.0.dist-info/METADATA
warriornetwork-1.0.0.dist-info/WHEEL
warriornetwork-1.0.0.dist-info/top_level.txt
warriornetwork-1.0.0.dist-info/RECORD
